scapy_http/__init__.py
scapy_http/http.py
scapy_http-1.8.2.dist-info/METADATA
scapy_http-1.8.2.dist-info/RECORD
scapy_http-1.8.2.dist-info/WHEEL
scapy_http-1.8.2.dist-info/top_level.txt
