Metadata-Version: 1.1
Name: scapy-http
Version: 1.8.2
Summary: HTTP-layer support for Scapy
Home-page: https://github.com/invernizzi/scapy-http
Author: ['Luca Invernizzi, Steeve Barbeau']
Author-email: invernizzi.l@gmail.com
License: UNKNOWN
Download-URL: https://github.com/invernizzi/scapy-http/tarball/1.8.2
Keywords: http,scapy,newtork,dissect,packets
Platform: UNKNOWN
